pycalgo/__init__.py
pycalgo/calculator.dll
pycalgo/calculator.dylib
pycalgo/calculator.so
pycalgo/pycal.py
pycalgo-0.3.0.dist-info/METADATA
pycalgo-0.3.0.dist-info/WHEEL
pycalgo-0.3.0.dist-info/top_level.txt
pycalgo-0.3.0.dist-info/RECORD
